[
    {
        "album_name": "Coser@星之迟迟 - 矢澤妮可",
        "file_name": "0001.jpg",
        "id": "1pceC7uqtE6_jWtw2Pk0Qi2HN8MQLXOIU"
    },
    {
        "album_name": "Coser@星之迟迟 - 矢澤妮可",
        "file_name": "002.jpg",
        "id": "1pMPy43X-heGFrnc3qBg3f8SBQ8XOgSWF"
    },
    {
        "album_name": "Coser@星之迟迟 - 矢澤妮可",
        "file_name": "003.jpg",
        "id": "1opvQeohW3AA_tLUxYbhK_pBHKY_v45MR"
    },
    {
        "album_name": "Coser@星之迟迟 - 矢澤妮可",
        "file_name": "004.jpg",
        "id": "1pOa1dq6v-si6zXLYdFM2Ybnh7b3GubeK"
    },
    {
        "album_name": "Coser@星之迟迟 - 矢澤妮可",
        "file_name": "005.jpg",
        "id": "1oTb_8rtPg5zkPaQj0NaT-KQ38RUc0b7U"
    },
    {
        "album_name": "Coser@星之迟迟 - 矢澤妮可",
        "file_name": "006.jpg",
        "id": "1pWrD3S_AL2tmiju5fzqRbsVOiZC7o-gf"
    },
    {
        "album_name": "Coser@星之迟迟 - 矢澤妮可",
        "file_name": "007.jpg",
        "id": "1opAOmjDBwAi6PC1SCAGHKgDkY8Q0Qyol"
    },
    {
        "album_name": "Coser@星之迟迟 - 矢澤妮可",
        "file_name": "008.jpg",
        "id": "1ovHgfO7v9gC5uex2toxq2z7I-vyA17A8"
    },
    {
        "album_name": "Coser@星之迟迟 - 矢澤妮可",
        "file_name": "009.jpg",
        "id": "1pH4epL8no0bvS9jwEAWg46osrQaJ6d6_"
    },
    {
        "album_name": "Coser@星之迟迟 - 矢澤妮可",
        "file_name": "010.jpg",
        "id": "1owKWDhoJs-J9438JIpFh4WYVvmdFb831"
    },
    {
        "album_name": "Coser@星之迟迟 - 矢澤妮可",
        "file_name": "011.jpg",
        "id": "1pDsl-YnGGt381INuALXbJhcQewMWs5iA"
    },
    {
        "album_name": "Coser@星之迟迟 - 矢澤妮可",
        "file_name": "012.jpg",
        "id": "1pP71YvbWYWLqt6cC7ldbaWnff64oYueh"
    },
    {
        "album_name": "Coser@星之迟迟 - 矢澤妮可",
        "file_name": "013.jpg",
        "id": "1pHkmDSqRVjSmOShEOAU_M7v2vqR_gE1J"
    },
    {
        "album_name": "Coser@星之迟迟 - 矢澤妮可",
        "file_name": "014.jpg",
        "id": "1okckrULABP0zSze_VCxp1GT3J2Z7gohC"
    },
    {
        "album_name": "Coser@星之迟迟 - 矢澤妮可",
        "file_name": "015.jpg",
        "id": "1pFTpAbc6GvXH-NSf8U5JmT84OSbGuXT9"
    },
    {
        "album_name": "Coser@星之迟迟 - 矢澤妮可",
        "file_name": "016.jpg",
        "id": "1p6FxhvtlYsBnOhuMnv8D3zFkv8DVkOKq"
    },
    {
        "album_name": "Coser@星之迟迟 - 矢澤妮可",
        "file_name": "017.jpg",
        "id": "1p00AYfgzHP9RX5rw1-j3AKb5YWPe258e"
    },
    {
        "album_name": "Coser@星之迟迟 - 矢澤妮可",
        "file_name": "018.jpg",
        "id": "1p7NQm1DVLmv9ExzaDdqIBgM6ZvJTZiaw"
    },
    {
        "album_name": "Coser@星之迟迟 - 矢澤妮可",
        "file_name": "019.jpg",
        "id": "1olfWSPfEj4LzdIFvbLIcoGzBwtot9Dw-"
    },
    {
        "album_name": "Coser@星之迟迟 - 矢澤妮可",
        "file_name": "020.jpg",
        "id": "1oW7m23balJz38IePtnKo4rwRU34kZvqE"
    },
    {
        "album_name": "Coser@星之迟迟 - 矢澤妮可",
        "file_name": "021.jpg",
        "id": "1o_WqNR93AGMzkmv1MYUHJ6HU9Nw_-qTi"
    },
    {
        "album_name": "Coser@星之迟迟 - 矢澤妮可",
        "file_name": "022.jpg",
        "id": "1oQ2bOW80Lga9tRZP7riNBdnNwibe0Ti-"
    },
    {
        "album_name": "Coser@星之迟迟 - 矢澤妮可",
        "file_name": "023.jpg",
        "id": "1pP5huxOgIFDDc4gMLON7OIjuHQZRh4WB"
    },
    {
        "album_name": "Coser@星之迟迟 - 矢澤妮可",
        "file_name": "024.jpg",
        "id": "1oVo2OgKEoiTcYjhYyxlMtw0sgchzO34n"
    },
    {
        "album_name": "Coser@星之迟迟 - 矢澤妮可",
        "file_name": "025.jpg",
        "id": "1ofebC2ez_PkwRCRhEdlkx34xifFGtr5t"
    },
    {
        "album_name": "Coser@星之迟迟 - 矢澤妮可",
        "file_name": "026.jpg",
        "id": "1oicfV8ho1YA9vV2cUizj9VzLj3Ibjfcp"
    },
    {
        "album_name": "Coser@星之迟迟 - 矢澤妮可",
        "file_name": "027.jpg",
        "id": "1p2iwc-opoX4i4mFoS94J2yWW0ja2zHMq"
    },
    {
        "album_name": "Coser@星之迟迟 - 矢澤妮可",
        "file_name": "028.jpg",
        "id": "1p039pNvMvfRWsrcqH80JYsZizc8o5yF0"
    },
    {
        "album_name": "Coser@星之迟迟 - 矢澤妮可",
        "file_name": "029.jpg",
        "id": "1pTmBBGBJrrmg7m11V7nWNZsz9Ft1Kqqv"
    },
    {
        "album_name": "Coser@星之迟迟 - 矢澤妮可",
        "file_name": "030.jpg",
        "id": "1p5Vtjq7XTvQt2roY4uuYuDCIYv3VMBKC"
    },
    {
        "album_name": "Coser@星之迟迟 - 矢澤妮可",
        "file_name": "031.jpg",
        "id": "1pA4-BpHVkJzkPZONCV13sT_nPeR9ITf7"
    },
    {
        "album_name": "Coser@星之迟迟 - 矢澤妮可",
        "file_name": "032.jpg",
        "id": "1pRUdL6Qlhm6ek_xOaj-CtQ0w67MQtRn9"
    },
    {
        "album_name": "Coser@星之迟迟 - 矢澤妮可",
        "file_name": "033.jpg",
        "id": "1oh-_cdlM96c8xOQ-XjghPMYd7Mah_luk"
    },
    {
        "album_name": "Coser@星之迟迟 - 矢澤妮可",
        "file_name": "034.jpg",
        "id": "1pO2TJBQA3n-LhCOhLx5ibRLXmSXQcxWn"
    },
    {
        "album_name": "Coser@星之迟迟 - 矢澤妮可",
        "file_name": "035.jpg",
        "id": "1pQodgMc1kmSYuFg8wV_MzZPQPtW0IY4I"
    },
    {
        "album_name": "Coser@星之迟迟 - 矢澤妮可",
        "file_name": "036.jpg",
        "id": "1onfeB4VWZkrESyrrTwav_PkzEQeIqkSy"
    },
    {
        "album_name": "Coser@星之迟迟 - 矢澤妮可",
        "file_name": "037.jpg",
        "id": "1ou8JqO18Hvdhxe-gGwzaS72b8omrg7WG"
    },
    {
        "album_name": "Coser@星之迟迟 - 矢澤妮可",
        "file_name": "038.jpg",
        "id": "1p5WifXKzkbBmPY1BjgK9plcvF9cfrmyq"
    },
    {
        "album_name": "Coser@星之迟迟 - 矢澤妮可",
        "file_name": "039.jpg",
        "id": "1oc3touMMp0KmDbWEtwpu4U-hPkiIxhCT"
    }
]